sine_wave/__init__.py
sine_wave/sine_wave.py
sine_wave_package2-0.1.dist-info/METADATA
sine_wave_package2-0.1.dist-info/WHEEL
sine_wave_package2-0.1.dist-info/entry_points.txt
sine_wave_package2-0.1.dist-info/top_level.txt
sine_wave_package2-0.1.dist-info/RECORD
